rm_api/__init__.py
rm_api/auth.py
rm_api/defaults.py
rm_api/download_lock.py
rm_api/helpers.py
rm_api/models.py
rm_api/notifications/__init__.py
rm_api/notifications/models.py
rm_api/notifications/websocket.py
rm_api/storage/__init__.py
rm_api/storage/common.py
rm_api/storage/exceptions.py
rm_api/storage/new_sync.py
rm_api/storage/old_sync.py
rm_api/storage/v3.py
rm_api/sync_stages.py
rm_api/templates.py
rm_api/tests/__init__.py
rm_api/tests/common.py
rm_api/tests/files/content/first_page.json
rm_api/tests/files/content/last_page_visited.json
rm_api/tests/files/content/pdf_redirect.json
rm_api/tests/files/content/pdf_zoom_custom.json
rm_api/tests/files/content/pdf_zoom_height.json
rm_api/tests/files/content/pdf_zoom_width.json
rm_api/tests/files/metadata/001.json
rm_api/tests/test_001_models.py
rm_api-1.1.1.dist-info/LICENSE
rm_api-1.1.1.dist-info/METADATA
rm_api-1.1.1.dist-info/WHEEL
rm_api-1.1.1.dist-info/RECORD
