Metadata-Version: 2.3
Name: rm-api
Version: 1.1.1
Summary: A python library to handle interactions with the reMarkable API.
License: LICENSE
Author: RedTTG
Author-email: red@redttg.com
Requires-Python: >=3.9
Classifier: License :: Other/Proprietary License
Classifier: Programming Language :: Python :: 3
Classifier: Programming Language :: Python :: 3.9
Classifier: Programming Language :: Python :: 3.10
Classifier: Programming Language :: Python :: 3.11
Classifier: Programming Language :: Python :: 3.12
Classifier: Programming Language :: Python :: 3.13
Requires-Dist: aiohttp (>=3.11.6,<3.12.0)
Requires-Dist: colorama (>=0.4.6,<0.5.0)
Requires-Dist: crc32c (>=2.7.1,<2.8.0)
Requires-Dist: httpx (>=0.27.2,<0.28.0)
Requires-Dist: packaging (>=24.2,<25.0)
Requires-Dist: pyjwt (>=2.9.0,<2.10.0)
Requires-Dist: pypdf2 (>=3.0.1,<3.1.0)
Requires-Dist: requests (>=2.32.3,<2.33.0)
Requires-Dist: websocket-client (>=1.8.0,<1.9.0)
